[{"_id":"5dddadb21b3e58e6694cb8a652029a02","_rev":"1-92c58708670a83e5bd44baf05e347220","userId":"0ca5fd605dc8ae50fb6e2d312b00c62b","checkout":[{"_id":"c70debcf1cd36500d6bb51647800dca2","_rev":"1-690b07d0edd0d5d92a6e9ad1e39b772e","Marke":"Rolex","Modell":"Sky-Dweller Gelbgold","Artikel":"ak3715","Preis":69990,"Typ":"Herrenuhr","Jahr":"2016","Gehaeuse":"Gelbgold","Armband":"Gelbgold","Uhrwerk":"Automatik","Ziffernblatt":"Gold","Glas":"Saphirglas","Durchmesser":"42.0 mm","Besonderheiten":["Verschraubte Krone","Datum","Drehbare Lünette","Brilliantbesatz der Lünette","Brilliantbesatz des Zifferblattes","Faltschließe","GMT / 2. Zeitzone"],"images":["./images/ak3715/img_5562.jpg","./images/ak3715/img_5563.jpg","./images/ak3715/img_5564.jpg","./images/ak3715/img_5565.jpg","./images/ak3715/img_5566.jpg"],"Anzahl":1,"localeTime":1615391467631},{"_id":"c70debcf1cd36500d6bb51647800d1cb","_rev":"1-8199dcb6e9fa29de25def58a067fe75b","Marke":"Rolex","Modell":"Submariner","Artikel":"ak3786","Preis":30990,"Typ":"Herrenuhr","Jahr":"2015","Gehaeuse":"Gelbgold","Armband":"Gelbgold","Uhrwerk":"Automatik","Ziffernblatt":"Schwarz","Glas":"Saphirglas","Durchmesser":"40.0 mm","Besonderheiten":["Verschraubte Krone","Datum","Drehbare Lünette","Faltschließe"],"images":["./images/ak3786/img_6680.jpg","./images/ak3786/img_6681.jpg","./images/ak3786/img_6682.jpg","./images/ak3786/img_6683.jpg","./images/ak3786/img_6684.jpg"],"Anzahl":1,"localeTime":1615391467631},{"_id":"c70debcf1cd36500d6bb51647800ee36","_rev":"1-fcce518327c04df28acd34eb41208529","Marke":"Rolex","Modell":"Daytona Weißgold","Artikel":"kk3492","Preis":24990,"Typ":"Herrenuhr","Jahr":"2014","Gehaeuse":"Weißgold","Armband":"Weißgold","Uhrwerk":"Automatik","Ziffernblatt":"Schwarz","Glas":"Saphirglas","Durchmesser":"40.0 mm","Besonderheiten":["Kleine Sekunde","Verschraubte Krone","Verschraubte Drücker","Chronograph","Faltschließe"],"images":["./images/kk3492/img_2167_1.jpg","./images/kk3492/img_2168_1.jpg","./images/kk3492/img_2169_1.jpg","./images/kk3492/img_2170_1.jpg","./images/kk3492/img_2172_1.jpg"],"Anzahl":1,"localeTime":1615391467631}]}]